server.py
mssql_py_mcp/__init__.py
mssql_py_mcp/app_config.py
mssql_py_mcp/core.py
mssql_py_mcp-0.1.3.dist-info/METADATA
mssql_py_mcp-0.1.3.dist-info/WHEEL
mssql_py_mcp-0.1.3.dist-info/entry_points.txt
mssql_py_mcp-0.1.3.dist-info/top_level.txt
mssql_py_mcp-0.1.3.dist-info/RECORD
