Metadata-Version: 2.4
Name: mssql-py-mcp
Version: 0.1.3
Summary: A MSSQL MCP server using pure Python TDS
Author-email: JEWEI AI <jewei@jewei.tech>
Requires-Python: >=3.10
Requires-Dist: fastmcp>=0.1.0
Requires-Dist: python-tds>=1.13.0
Requires-Dist: python-dotenv>=0.19.0
Provides-Extra: dev
Requires-Dist: pytest>=7.0.0; extra == "dev"
Requires-Dist: pytest-asyncio>=0.21.0; extra == "dev"
